inlp/__init__.py
inlp/lang.py
inlp/pos.py
inlp/tokenize.py
inlp/tests/__init__.py
inlp/tests/pos.py
inlp/tests/tokenize.py
i_nlp-0.0.3.dist-info/LICENSE
i_nlp-0.0.3.dist-info/METADATA
i_nlp-0.0.3.dist-info/WHEEL
i_nlp-0.0.3.dist-info/top_level.txt
i_nlp-0.0.3.dist-info/RECORD
