Metadata-Version: 2.1
Name: i-nlp
Version: 0.0.3
Summary: innovata-nlp
Home-page: https://github.com/innovata/inlp
Author: innovata sambong
Author-email: iinnovata@gmail.com
License: UNKNOWN
Platform: UNKNOWN
Classifier: Programming Language :: Python :: 3
Classifier: License :: OSI Approved :: MIT License
Classifier: Operating System :: OS Independent
